{
  "id": 1222300,
  "title": "Into The Flames",
  "cover": "https://cdn.cloudflare.steamstatic.com/steam/apps/1222300/capsule_616x353.jpg",
  "hero": "https://cdn.cloudflare.steamstatic.com/steam/apps/1222300/library_hero.jpg",
  "description": "Into the Flames is an open world firefighting game that can be played solo or with up to 12 other players online. Fill the role of a firefighter by driving the trucks to emergencies, and using authentic tools to get the job done.\n\r\n\n\r\nEmergencies take place in a variety of environments including suburbs, commercial businesses, and rural farm land. Emergencies include structure fires, hazardous gas leaks, propane tanks fire, and more! More emergencies are being added over time. \n\r\n\n\r\nThere are quite a few vehicles to choose from including multiple engines, rescues, and a tiller. Players can also assume the role of a volunteer, drive cars, and a Command SUV. More vehicles are being added over time.\n\r\n\n\r\nThere are plenty of tools to get any job done. Break down doors with an Axe, or knock down an electrical fire with an extinguisher. Most emergencies have multiple ways to tackle them with the given tools.\n\r\n\n\r\nThis game is constantly evolving, and getting new content. Please join the discord to talk to the developers, and help sculpt the future of Into The Flames.",
  "description_short": "Into The Flames is a Solo/Co-op firefighting game that focuses on the intensity of being a real life firefighter. Drive emergency vehicles, bust down doors, fight raging fires, and do whatever it takes to bring the chaotic scene under control!",
  "genres": [
    "Технические симуляторы",
    "Экшен",
    "Казуальные игры",
    "Песочницы (Sandbox)",
    "Шутеры от третьего лица (TPS)",
    "Шутеры от первого лица (FPS)"
  ],
  "platforms": [
    "PC"
  ],
  "base_price_rub": 477,
  "markup_rub": 500,
  "price_rub": 977,
  "original_price_rub": null,
  "discount_percent": 0,
  "is_free": false,
  "trailer_video": null,
  "trailer_youtube_id": null,
  "screenshots": [
    "https://shared.akamai.steamstatic.com/store_item_assets/steam/apps/1222300/ss_bd806ec49da9bbf14f2845c5faaf462c421bf090.1920x1080.jpg?t=1783340148",
    "https://shared.akamai.steamstatic.com/store_item_assets/steam/apps/1222300/ss_977c6cf5b264e6633410a398410998d1bfefae5f.1920x1080.jpg?t=1783340148",
    "https://shared.akamai.steamstatic.com/store_item_assets/steam/apps/1222300/ss_751272d076fa5db424de9efa593a2ff3c113a818.1920x1080.jpg?t=1783340148",
    "https://shared.akamai.steamstatic.com/store_item_assets/steam/apps/1222300/ss_dd984d24a6dec17bc97424b659f639bea61893ed.1920x1080.jpg?t=1783340148",
    "https://shared.akamai.steamstatic.com/store_item_assets/steam/apps/1222300/ss_84aae97f095b99709c8acd0660be1f64993b0845.1920x1080.jpg?t=1783340148",
    "https://shared.akamai.steamstatic.com/store_item_assets/steam/apps/1222300/ss_012adfdec55005d4bd5cd803932df0efad10a928.1920x1080.jpg?t=1783340148",
    "https://shared.akamai.steamstatic.com/store_item_assets/steam/apps/1222300/ss_3601b6ffd0676faf5a47e813559afa9169fd0f07.1920x1080.jpg?t=1783340148",
    "https://shared.akamai.steamstatic.com/store_item_assets/steam/apps/1222300/ss_db63c0750434bd02ba69bf300e8a72725658635a.1920x1080.jpg?t=1783340148"
  ],
  "upsells": [
    {
      "id": 1381670,
      "name": "Into The Flames - Supporter Pack",
      "base_price_rub": 127,
      "markup_rub": 500,
      "price_rub": 627,
      "cover": "https://shared.akamai.steamstatic.com/store_item_assets/steam/apps/1381670/header.jpg?t=1673364180"
    },
    {
      "id": 2406820,
      "name": "Into The Flames - Retro Fire Gear 1",
      "base_price_rub": 127,
      "markup_rub": 500,
      "price_rub": 627,
      "cover": "https://shared.akamai.steamstatic.com/store_item_assets/steam/apps/2406820/header.jpg?t=1689278727"
    },
    {
      "id": 2406821,
      "name": "Into The Flames - Retro Truck Pack 1",
      "base_price_rub": 212,
      "markup_rub": 500,
      "price_rub": 712,
      "cover": "https://shared.akamai.steamstatic.com/store_item_assets/steam/apps/2406821/header.jpg?t=1688074307"
    },
    {
      "id": 2560300,
      "name": "Into The Flames - Retro Truck Pack 2",
      "base_price_rub": 212,
      "markup_rub": 500,
      "price_rub": 712,
      "cover": "https://shared.akamai.steamstatic.com/store_item_assets/steam/apps/2560300/header.jpg?t=1708901193"
    },
    {
      "id": 2641290,
      "name": "Rescue Truck Pack 1",
      "base_price_rub": 212,
      "markup_rub": 500,
      "price_rub": 712,
      "cover": "https://shared.akamai.steamstatic.com/store_item_assets/steam/apps/2641290/header.jpg?t=1722447990"
    },
    {
      "id": 2664030,
      "name": "Into The Flames - Spooky Pack",
      "base_price_rub": 169,
      "markup_rub": 500,
      "price_rub": 669,
      "cover": "https://shared.akamai.steamstatic.com/store_item_assets/steam/apps/2664030/header.jpg?t=1704416881"
    },
    {
      "id": 2752060,
      "name": "Into The Flames - Support Vehicle Pack",
      "base_price_rub": 212,
      "markup_rub": 500,
      "price_rub": 712,
      "cover": "https://shared.akamai.steamstatic.com/store_item_assets/steam/apps/2752060/header.jpg?t=1704143422"
    },
    {
      "id": 2752070,
      "name": "Into The Flames - Tower Ladder Vehicle",
      "base_price_rub": 212,
      "markup_rub": 500,
      "price_rub": 712,
      "cover": "https://shared.akamai.steamstatic.com/store_item_assets/steam/apps/2752070/header.jpg?t=1711304081"
    },
    {
      "id": 2763100,
      "name": "Into The Flames - Supporter Pack 2",
      "base_price_rub": 320,
      "markup_rub": 500,
      "price_rub": 820,
      "cover": "https://shared.akamai.steamstatic.com/store_item_assets/steam/apps/2763100/header.jpg?t=1733881001"
    },
    {
      "id": 2942360,
      "name": "Into The Flames - Tiller Pack",
      "base_price_rub": 320,
      "markup_rub": 500,
      "price_rub": 820,
      "cover": "https://shared.akamai.steamstatic.com/store_item_assets/steam/apps/2942360/2056f29f55b05cf77d8cc3d4a34aed0fd5c7b5ea/header.jpg?t=1774029920"
    }
  ],
  "source": "steam",
  "updated_at": "2026-07-10T20:20:03Z"
}