{
  "id": 1454400,
  "title": "Cookie Clicker",
  "cover": "https://cdn.cloudflare.steamstatic.com/steam/apps/1454400/capsule_616x353.jpg",
  "hero": "https://cdn.cloudflare.steamstatic.com/steam/apps/1454400/library_hero.jpg",
  "description": "В игре Cookie Clicker нужно производить абсурдное количество печенья. В помощь себе можно нанять самых разных помощников: добрых бабушек, фермы, фабрики и инопланетные порталы.\n\nИгра Cookie Clicker вышла в 2013 году и с тех пор активно развивалась. Если вы играли раньше, то попробуйте снова и взгляните на новые функции!\n\n• Копите печенье и тратьте его на другое печенье!\n\n• Более 600 улучшений\n\n• Более 500 достижений\n\n• Побалуйте своего дракона\n\n• Миниигры\n\n• Откройте божественные постоянные улучшения\n\n• Облачное сохранение (больше вы не удалите печенье случайно)\n\n• Музыка авторства C418",
  "description_short": "Неспешная игра о выпечке печенья! Вышла в 2013 году в сети, с тех пор активно развивалась, и это ее официальная версия в Steam.",
  "genres": [
    "Казуальные игры",
    "Психологические хорроры",
    "Экономические симуляторы",
    "Технические симуляторы"
  ],
  "platforms": [
    "PC"
  ],
  "base_price_rub": 107,
  "markup_rub": 500,
  "price_rub": 607,
  "original_price_rub": 715,
  "discount_percent": 50,
  "is_free": false,
  "trailer_video": null,
  "trailer_youtube_id": null,
  "screenshots": [
    "https://shared.akamai.steamstatic.com/store_item_assets/steam/apps/1454400/ss_4e2e8d83a12afe9adeb7b24f4ef3d0d22a2ecd08.1920x1080.jpg?t=1782425712",
    "https://shared.akamai.steamstatic.com/store_item_assets/steam/apps/1454400/ss_e579d4e05346d61568ca209b08a1eab87aa93e98.1920x1080.jpg?t=1782425712",
    "https://shared.akamai.steamstatic.com/store_item_assets/steam/apps/1454400/ss_197f3259b916e48563fcdea9c75dd8bc4e7dda1e.1920x1080.jpg?t=1782425712",
    "https://shared.akamai.steamstatic.com/store_item_assets/steam/apps/1454400/ss_93eea05255639eaf370ad9cdfa6843028409ceab.1920x1080.jpg?t=1782425712",
    "https://shared.akamai.steamstatic.com/store_item_assets/steam/apps/1454400/ss_e85f9565b30775f652aef9cc0c086087477ccea7.1920x1080.jpg?t=1782425712",
    "https://shared.akamai.steamstatic.com/store_item_assets/steam/apps/1454400/ss_ddfa1b63f478ab696bf5f9f3f75c8558106832f7.1920x1080.jpg?t=1782425712",
    "https://shared.akamai.steamstatic.com/store_item_assets/steam/apps/1454400/ss_ed3c765c6c62d4aaae28e83ec7b50af5977e66fa.1920x1080.jpg?t=1782425712"
  ],
  "upsells": [
    {
      "id": 1738020,
      "name": "Cookie Clicker Soundtrack",
      "base_price_rub": 213,
      "markup_rub": 500,
      "price_rub": 713,
      "cover": "https://shared.akamai.steamstatic.com/store_item_assets/steam/apps/1738020/header.jpg?t=1630789694"
    }
  ],
  "source": "steam",
  "updated_at": "2026-07-09T10:00:18Z"
}