{
  "id": 1456820,
  "title": "溶鉄のマルフーシャ",
  "cover": "https://cdn.cloudflare.steamstatic.com/steam/apps/1456820/capsule_616x353.jpg",
  "hero": "https://cdn.cloudflare.steamstatic.com/steam/apps/1456820/library_hero.jpg",
  "description": "A high-tempo shooting game with simple controls!\n\r\nBecome a guard of a dystopian world and defend the border gates from the enemies.\n\r\n\n\r\nUpgrade your character by buying cards with your heavily-taxed salary to face increasingly powerful enemies.\n\r\n\n\r\n-Cards for weapons, characters, power-ups, chance events, etc.\n\r\n-8 kinds of unique characters\n\r\n-Score attack ranking",
  "description_short": "A high-tempo shooting game with simple controls! Upgrade your character with cards and defend the gates from your enemies.",
  "genres": [
    "Шутеры от первого лица (FPS)",
    "Башенная защита (Tower Defense)",
    "Экшен"
  ],
  "platforms": [
    "PC"
  ],
  "base_price_rub": 257,
  "markup_rub": 500,
  "price_rub": 757,
  "original_price_rub": null,
  "discount_percent": 0,
  "is_free": false,
  "trailer_video": null,
  "trailer_youtube_id": null,
  "screenshots": [
    "https://shared.akamai.steamstatic.com/store_item_assets/steam/apps/1456820/ss_e5aedc4fdf408611ade78bf54d93f476e409ced7.1920x1080.jpg?t=1745453945",
    "https://shared.akamai.steamstatic.com/store_item_assets/steam/apps/1456820/ss_af2a3815a4fac5560ad6a3058519abdbc474cf65.1920x1080.jpg?t=1745453945",
    "https://shared.akamai.steamstatic.com/store_item_assets/steam/apps/1456820/ss_8505cd3ef3b6d3651483c122d033d9e99b59d599.1920x1080.jpg?t=1745453945",
    "https://shared.akamai.steamstatic.com/store_item_assets/steam/apps/1456820/ss_e4e59759caa110330f3eca7e97bdf98a28c87586.1920x1080.jpg?t=1745453945",
    "https://shared.akamai.steamstatic.com/store_item_assets/steam/apps/1456820/ss_0efafad6980e9bf43ef60e4809432c99e1993fa5.1920x1080.jpg?t=1745453945",
    "https://shared.akamai.steamstatic.com/store_item_assets/steam/apps/1456820/ss_b94f3a8a348c1dfbd13eb6fc8ac494e3d714dfbb.1920x1080.jpg?t=1745453945",
    "https://shared.akamai.steamstatic.com/store_item_assets/steam/apps/1456820/ss_ba6b162e65d7a84973a99ec5679c6b6a5e1c3c85.1920x1080.jpg?t=1745453945",
    "https://shared.akamai.steamstatic.com/store_item_assets/steam/apps/1456820/ss_435c8353b64d4d6349f0a01352297f811888c53d.1920x1080.jpg?t=1745453945"
  ],
  "upsells": [
    {
      "id": 1512080,
      "name": "溶鉄のマルフーシャアートブック",
      "base_price_rub": 69,
      "markup_rub": 500,
      "price_rub": 569,
      "cover": "https://shared.akamai.steamstatic.com/store_item_assets/steam/apps/1512080/header.jpg?t=1662569423"
    }
  ],
  "source": "steam",
  "updated_at": "2026-07-13T15:17:57Z"
}