{
  "id": 1667320,
  "title": "PRODUCER 2021",
  "cover": "https://cdn.cloudflare.steamstatic.com/steam/apps/1667320/capsule_616x353.jpg",
  "hero": "https://cdn.cloudflare.steamstatic.com/steam/apps/1667320/library_hero.jpg",
  "description": "Producer (2021) is a graphic adventure novella.\n\nWoken by a phone you never bought, you quickly find yourself hired by a nebolous company. You're the producer now. Tasked with disrupting the end of the world, you explore, investigate and produce your way through a strangely familiar world. \n\nThe job itself is easy enough, but do you have it in yourself to be enthusiastic? \nWill you get to tbe bottom of all the weirdness?\nAnd actually...\n... what even is a producer?\n\nPRODUCER 2021 is ~2 hours long and contains 25+ tracks of original music by ThorHighHeels.\nAvailable in english.\nFull of bad words.\nNo achievements.",
  "description_short": "a ~2 hour long graphic adventure novella. Tasked with disrupting the end of the world, you explore, investigate and produce your way through a strangely familiar world.",
  "genres": [
    "Приключения",
    "Интерактивное кино",
    "Квесты (Point-and-Click)",
    "Визуальные новеллы",
    "Классические ролевые игры (CRPG)",
    "Иммерсивные симуляторы (Immersive Sim)"
  ],
  "platforms": [
    "PC"
  ],
  "base_price_rub": 387,
  "markup_rub": 500,
  "price_rub": 887,
  "original_price_rub": null,
  "discount_percent": 0,
  "is_free": false,
  "trailer_video": null,
  "trailer_youtube_id": null,
  "screenshots": [
    "https://shared.akamai.steamstatic.com/store_item_assets/steam/apps/1667320/ss_62397584846f2e3da6b789ef50a27022aa2a3950.1920x1080.jpg?t=1671045269",
    "https://shared.akamai.steamstatic.com/store_item_assets/steam/apps/1667320/ss_00be9b0b2659089a419e91f0fca0fc1812298f03.1920x1080.jpg?t=1671045269",
    "https://shared.akamai.steamstatic.com/store_item_assets/steam/apps/1667320/ss_aa110205682b2c3824d51914173c0b4ab4a79738.1920x1080.jpg?t=1671045269",
    "https://shared.akamai.steamstatic.com/store_item_assets/steam/apps/1667320/ss_32725d510f2e1c934e4842361bdff56340796959.1920x1080.jpg?t=1671045269",
    "https://shared.akamai.steamstatic.com/store_item_assets/steam/apps/1667320/ss_15d841a5fcb90c3bc85f6540f5dd5933fb59c07d.1920x1080.jpg?t=1671045269",
    "https://shared.akamai.steamstatic.com/store_item_assets/steam/apps/1667320/ss_bda0defdb5ca922034b40f82c240905f8cb745b2.1920x1080.jpg?t=1671045269",
    "https://shared.akamai.steamstatic.com/store_item_assets/steam/apps/1667320/ss_7fb43305f869e99137c944dfe9b2f1a88889d4be.1920x1080.jpg?t=1671045269",
    "https://shared.akamai.steamstatic.com/store_item_assets/steam/apps/1667320/ss_31475a5c4d54b9528fed062d8c5822a303a18990.1920x1080.jpg?t=1671045269"
  ],
  "upsells": [],
  "source": "steam",
  "updated_at": "2026-07-12T04:11:36Z"
}