{
  "id": 20510,
  "title": "S.T.A.L.K.E.R.: Clear Sky",
  "cover": "https://cdn.cloudflare.steamstatic.com/steam/apps/20510/capsule_616x353.jpg",
  "hero": "https://cdn.cloudflare.steamstatic.com/steam/apps/20510/library_hero.jpg",
  "description": "S.T.A.L.K.E.R. 2: Сердце Чернобыля\n\nПриготовьтесь войти в Зону на свой страх и риск, стремясь разбогатеть на этом или даже найти Истину, сокрытую в Сердце Чернобыля.\n\n* ЭПИЧНАЯ НЕЛИНЕЙНАЯ ИСТОРИЯ В БЕСШОВНОМ ОТКРЫТОМ МИРЕ\n* РАЗНООБРАЗНЫЕ ВРАГИ И СОТНИ КОМБИНАЦИЙ ОРУЖИЯ \n* ЛЕГЕНДАРНЫЕ МУТАНТЫ С РАЗЛИЧНЫМИ МОДЕЛЯМИ ПОВЕДЕНИЯ \n* АРТЕФАКТЫ НЕВЕРОЯТНОЙ ЦЕННОСТИ И БЕСПОЩАДНЫЕ АНОМАЛИИ \n\nОткройте для себя легендарную вселенную S.T.A.L.K.E.R.!\n\nОб игреБольшой Выброс, сильнейший со времен Второй Катастрофы взрыв аномальной энергии из реактора Чернобыльской Атомной Электростанции, вновь сотряс мироздание и перекроил Зону. Установить его причины и предотвратить повтор — ваш единственный шанс сохранить жизнь в S.T.A.L.K.E.R.: Clear Sky.ВОЙНА ГРУППИРОВОК\nТурбулентность Зоны нарушила и так хрупкий баланс сил группировок и фракций. Теперь в каждом её уголке не утихают битвы за новые территории, поля артефактов и сферы влияния. Больше нет старых врагов или друзей — каждый сам за себя! Чтобы выжить, присоединяйтесь к одной из сторон и выбейте противников за Кордон… Или же извлекайте выгоду от одновременной работы на противников, словно истинный наемник.НОВЫЕ ТРОПЫ\nБольше нет проверенных и безопасных дорог. Известные места пропадают в непроходимых полях аномалий, сталкеры и целые экспедиции гибнут или остаются взаперти. Открываются и влекут исследователей загадочные территории, утерянные со времен появления Зоны. Стать первопроходцем — ваша миссия в “Чистом Небе”!ТАЙНЫ ПРОШЛОГО\nВ роли наемника Шрама, сыграйте ключевую роль в судьбе Стрелка и предопределите историю оригинальной игры, проливая свет на её главные загадки. Посетите знакомые места задолго до действий предыдущей части серии и станьте участником событий, которые сформировали Зону на годы вперед.\n\nОсобенности игры:\n\n• Приквел S.T.A.L.K.E.R.: Shadow of Chernobyl, раскрывающий предысторию Зоны, знакомых персонажей и локаций.\n\n• Новые виды снаряжения и оружия: ХПСС-1м, охотничье ружье, РП-74.\n\n• Новые локации: Болота, Рыжий лес, Лиманск и Заброшенный госпиталь, полные новых историй и заданий.\n\n• Развитая система улучшений оружия и брони у техников, позволяющая улучшить и настроить под себя любимые модели.\n\n• Влияние действий игрока на расстановку сил в Зоне и отношение фракций\n\n• Дюжина новых аномалий и артефактов, а также новая система их поиска и добычи при помощи детектора. \n\n• Улучшенная графика, интерфейс и ИИ, делающие путешествие по хмурым радиоактивных землям ещё более завораживающим.",
  "description_short": "S.T.A.L.K.E.R.: Чистое Небо – самостоятельный приквел к знаменитой S.T.A.L.K.E.R.: Тень Чернобыля, который рассказывает вам историю группировки Чистое Небо, которая исследует Зону и хочет ее понять.",
  "genres": [
    "Песочницы (Sandbox)",
    "Шутеры от первого лица (FPS)",
    "Выживание (Survival)",
    "Экшен",
    "Хорроры на выживание (Survival Horror)",
    "Приключения"
  ],
  "platforms": [
    "PC"
  ],
  "base_price_rub": 713,
  "markup_rub": 500,
  "price_rub": 1213,
  "original_price_rub": null,
  "discount_percent": 0,
  "is_free": false,
  "trailer_video": null,
  "trailer_youtube_id": null,
  "screenshots": [
    "https://shared.akamai.steamstatic.com/store_item_assets/steam/apps/20510/0000002636.1920x1080.jpg?t=1747756044",
    "https://shared.akamai.steamstatic.com/store_item_assets/steam/apps/20510/0000002637.1920x1080.jpg?t=1747756044",
    "https://shared.akamai.steamstatic.com/store_item_assets/steam/apps/20510/0000002638.1920x1080.jpg?t=1747756044",
    "https://shared.akamai.steamstatic.com/store_item_assets/steam/apps/20510/0000002639.1920x1080.jpg?t=1747756044",
    "https://shared.akamai.steamstatic.com/store_item_assets/steam/apps/20510/0000002640.1920x1080.jpg?t=1747756044",
    "https://shared.akamai.steamstatic.com/store_item_assets/steam/apps/20510/0000002641.1920x1080.jpg?t=1747756044",
    "https://shared.akamai.steamstatic.com/store_item_assets/steam/apps/20510/0000002642.1920x1080.jpg?t=1747756044",
    "https://shared.akamai.steamstatic.com/store_item_assets/steam/apps/20510/0000002643.1920x1080.jpg?t=1747756044"
  ],
  "upsells": [],
  "source": "steam",
  "updated_at": "2026-07-09T15:37:17Z"
}