{
  "id": 2202470,
  "title": "No Sun To Worship",
  "cover": "https://cdn.cloudflare.steamstatic.com/steam/apps/2202470/capsule_616x353.jpg",
  "hero": "https://cdn.cloudflare.steamstatic.com/steam/apps/2202470/library_hero.jpg",
  "description": "A short, minimalist stealth-action game about the importance of art. \n\nLight, sound, stance and movement play a major role in how you hide from enemies. Stick to the shadows and sneak carefully!\n\nThere are multiple ways to complete your objective.\n\nReplay previous missions and beat your fastest times. You can also choose hard mode and get your ass kicked.\n\nUnravel the mystery of 'No Sun To Worship'. Who are you? Who are you killing and why? Pay attention to the symbolism and messaging.",
  "description_short": "A short, minimalist stealth-action game about the importance of art. We painted the sky ashen gray. Burned the heavens to starve each other. Now we walk an endless cemetery of regret.",
  "genres": [
    "Экшен",
    "Стелс-экшен",
    "Экшен-адвенчуры",
    "Шутеры от третьего лица (TPS)",
    "Шутеры от первого лица (FPS)"
  ],
  "platforms": [
    "PC"
  ],
  "base_price_rub": 322,
  "markup_rub": 500,
  "price_rub": 822,
  "original_price_rub": null,
  "discount_percent": 0,
  "is_free": false,
  "trailer_video": null,
  "trailer_youtube_id": null,
  "screenshots": [
    "https://shared.akamai.steamstatic.com/store_item_assets/steam/apps/2202470/ss_938afd1b44a9a7837035609dedcb75fb53f3f9cf.1920x1080.jpg?t=1753358842",
    "https://shared.akamai.steamstatic.com/store_item_assets/steam/apps/2202470/ss_9650e7071b316c4d77ffe291737f8730da59643a.1920x1080.jpg?t=1753358842",
    "https://shared.akamai.steamstatic.com/store_item_assets/steam/apps/2202470/ss_c7be5549368c708c09fe580864a518724d49716e.1920x1080.jpg?t=1753358842",
    "https://shared.akamai.steamstatic.com/store_item_assets/steam/apps/2202470/ss_52ce26bf4bf14d367f6ce6b68c4c5b0d082ba217.1920x1080.jpg?t=1753358842",
    "https://shared.akamai.steamstatic.com/store_item_assets/steam/apps/2202470/ss_c82e0696102b20790bece4ab942fda9092f4c823.1920x1080.jpg?t=1753358842",
    "https://shared.akamai.steamstatic.com/store_item_assets/steam/apps/2202470/ss_9f8ee0eda0a146ad497d593d577b09bebaf6b8ba.1920x1080.jpg?t=1753358842",
    "https://shared.akamai.steamstatic.com/store_item_assets/steam/apps/2202470/ss_000d6fe789ac7ebcc3984655d1dc6e6f51137ebb.1920x1080.jpg?t=1753358842",
    "https://shared.akamai.steamstatic.com/store_item_assets/steam/apps/2202470/ss_afd66821c835b0e882a14449911341c6eaca32c7.1920x1080.jpg?t=1753358842"
  ],
  "upsells": [],
  "source": "steam",
  "updated_at": "2026-07-14T19:54:24Z"
}