{
  "id": 2221920,
  "title": "Immortals Fenyx Rising",
  "cover": "https://cdn.cloudflare.steamstatic.com/steam/apps/2221920/capsule_616x353.jpg",
  "hero": "https://cdn.cloudflare.steamstatic.com/steam/apps/2221920/library_hero.jpg",
  "description": "Gold Edition\n\nОб игреПОСЛЕДНЯЯ НАДЕЖДА БОГОВ\n\nВам предстоит спасти греческих богов. \nСразитесь против мифических существ, овладейте силами богов и победите Тифона - самого могущественного титана.\n\nМИФИЧЕСКИЕ ПРОТИВНИКИ\nИспользуйте данные богами способности и оружие, чтобы одолеть легендарных существ: циклопа, горгону, минотавра и не только.\n\nМОЩЬ БОГОВ\nДары богов помогут вам сражаться с монстрами, разгадывать головоломки и исследовать открытый мир.",
  "description_short": "В Immortals Fenyx Rising вы отправитесь в увлекательное мифическое приключение. Ваш персонаж - Феникс. Вам предстоит спасти греческих богов.",
  "genres": [
    "Приключения",
    "Песочницы (Sandbox)",
    "Головоломки",
    "Экшен-адвенчуры",
    "Экшен-РПГ (Action-RPG)",
    "Экшен"
  ],
  "platforms": [
    "PC"
  ],
  "base_price_rub": 1486,
  "markup_rub": 500,
  "price_rub": 1986,
  "original_price_rub": null,
  "discount_percent": 0,
  "is_free": false,
  "trailer_video": null,
  "trailer_youtube_id": null,
  "screenshots": [
    "https://shared.akamai.steamstatic.com/store_item_assets/steam/apps/2221920/ss_daf49fac61e819a694723ebe4569a61f93ba098f.1920x1080.jpg?t=1778099749",
    "https://shared.akamai.steamstatic.com/store_item_assets/steam/apps/2221920/ss_05ac502dd26feb5f3ae138e7a9f0ad83bcd380e8.1920x1080.jpg?t=1778099749",
    "https://shared.akamai.steamstatic.com/store_item_assets/steam/apps/2221920/ss_5aee72d054c2b1e82803de174a4d486b08c9894d.1920x1080.jpg?t=1778099749",
    "https://shared.akamai.steamstatic.com/store_item_assets/steam/apps/2221920/ss_c5b6cd556904b521b201b62988902ef7d5904b56.1920x1080.jpg?t=1778099749",
    "https://shared.akamai.steamstatic.com/store_item_assets/steam/apps/2221920/ss_0c7f70cd0a7242dd679c9ede9b5a7c892f2aa66e.1920x1080.jpg?t=1778099749"
  ],
  "upsells": [
    {
      "id": 2224320,
      "name": "Immortals Fenyx Rising™ - Season Pass",
      "base_price_rub": 734,
      "markup_rub": 500,
      "price_rub": 1234,
      "cover": "https://shared.akamai.steamstatic.com/store_item_assets/steam/apps/2224320/header.jpg?t=1671127231"
    },
    {
      "id": 2222840,
      "name": "Immortals Fenyx Rising™ - A New God",
      "base_price_rub": 299,
      "markup_rub": 500,
      "price_rub": 799,
      "cover": "https://shared.akamai.steamstatic.com/store_item_assets/steam/apps/2222840/header.jpg?t=1671127202"
    },
    {
      "id": 2222841,
      "name": "Immortals Fenyx Rising™ - Myths of the Eastern Realm",
      "base_price_rub": 299,
      "markup_rub": 500,
      "price_rub": 799,
      "cover": "https://shared.akamai.steamstatic.com/store_item_assets/steam/apps/2222841/header.jpg?t=1671127176"
    },
    {
      "id": 2222842,
      "name": "Immortals Fenyx Rising™ -  The Lost Gods",
      "base_price_rub": 299,
      "markup_rub": 500,
      "price_rub": 799,
      "cover": "https://shared.akamai.steamstatic.com/store_item_assets/steam/apps/2222842/header.jpg?t=1671127134"
    }
  ],
  "source": "steam",
  "updated_at": "2026-07-10T20:01:06Z"
}