{
  "id": 261180,
  "title": "Lethal League",
  "cover": "https://cdn.cloudflare.steamstatic.com/steam/apps/261180/capsule_616x353.jpg",
  "hero": "https://cdn.cloudflare.steamstatic.com/steam/apps/261180/library_hero.jpg",
  "description": "В Lethal League ваша цель — попасть сопернику в лицо антигравитационным мячом.\n\r\n\n\r\nВозможности:\n\r\n– До 4 игроков: играйте локально или по интернету в трех режимах.\n\r\n\n\r\n– Сетевая игра: пригласите друзей или участвуйте в быстрой игре.\n\r\n\n\r\n– Легко освоить, трудно стать мастером: учитесь ударам, парированию и особым навыкам.\n\r\n\n\r\n– Уличная мода: все персонажи обладают уникальным стилем.\n\r\n\n\r\n– Испытания: сразитесь в аркадном режиме с группой соперников и доберитесь до босса.\n\r\n\n\r\n– Шикарный звук: биг-бит, хип-хоп и хаус.",
  "description_short": "В Lethal League ваша цель — попасть сопернику в лицо антигравитационным мячом.",
  "genres": [
    "Файтинги",
    "Экшен",
    "Спортивные симуляторы",
    "Аркадные гонки"
  ],
  "platforms": [
    "PC"
  ],
  "base_price_rub": 189,
  "markup_rub": 500,
  "price_rub": 689,
  "original_price_rub": 880,
  "discount_percent": 50,
  "is_free": false,
  "trailer_video": null,
  "trailer_youtube_id": null,
  "screenshots": [
    "https://shared.akamai.steamstatic.com/store_item_assets/steam/apps/261180/ss_cd5b1b2a8f7e5ec485355464fad326178e8616fa.1920x1080.jpg?t=1667229581",
    "https://shared.akamai.steamstatic.com/store_item_assets/steam/apps/261180/ss_63e59d6a7755475ff72c99c9b86bbaed789dbee2.1920x1080.jpg?t=1667229581",
    "https://shared.akamai.steamstatic.com/store_item_assets/steam/apps/261180/ss_dd3f69cd8cb18fce35255bdd51e0396905d62977.1920x1080.jpg?t=1667229581",
    "https://shared.akamai.steamstatic.com/store_item_assets/steam/apps/261180/ss_877948df067061526b4a82f957ad7d041686f782.1920x1080.jpg?t=1667229581",
    "https://shared.akamai.steamstatic.com/store_item_assets/steam/apps/261180/ss_7d7a964da3de6ad488e1ea3d4fb8a1f7ad2f2b90.1920x1080.jpg?t=1667229581",
    "https://shared.akamai.steamstatic.com/store_item_assets/steam/apps/261180/ss_4f68688fe6e7705e3f11dfac90f1ef269fcc2ab6.1920x1080.jpg?t=1667229581",
    "https://shared.akamai.steamstatic.com/store_item_assets/steam/apps/261180/ss_36647edce8fe6114156059a6a0d698a5aa41a183.1920x1080.jpg?t=1667229581",
    "https://shared.akamai.steamstatic.com/store_item_assets/steam/apps/261180/ss_b38769594cee271530a071e311d3b5fb46ea509c.1920x1080.jpg?t=1667229581"
  ],
  "upsells": [],
  "source": "steam",
  "updated_at": "2026-07-06T20:23:37Z"
}