{
  "id": 2792610,
  "title": "Stickman Killing Zombie",
  "cover": "https://cdn.cloudflare.steamstatic.com/steam/apps/2792610/capsule_616x353.jpg",
  "hero": "https://cdn.cloudflare.steamstatic.com/steam/apps/2792610/library_hero.jpg",
  "description": "The world of stickmen has a zombie epidemic - you must kill all the stickmen zombies become the new stickman hero ( the last stickman hero saved the stick world from zombies 20 years ago - you see, this is pretty common in the stickman world). \n\r\n\n\r\n- Simple controls for running and killing: Supports gamepad as well as keyboard\n\r\n- 3D world with zombies\n\r\n- Ragdoll zombie deaths\n\r\n- Steam Achievements\n\r\n- Gameplay designed to get you \"in the flow.\" You can listen to audiobooks n stuff as you play.\n\r\n\n\r\n\n\r\nYou never assumed your life as a stickman would get this violent.. but the world had other plans. You woke up and what you once loved became an infected cesspit. The city you once loved.. demeaned to this? You sigh as you get out your sword: this will be a long and bloody day.\n\r\n\n\r\nNow, good sir, no more time to speak! quick! Dash through the infected areas of Detroit and complete missions in the order you want.",
  "description_short": "The stickman world is in a zombie epidemic- kill zombie stickmen with your epic red sword!",
  "genres": [
    "Экшен",
    "Приключения",
    "Экшен-адвенчуры",
    "Аркадные гонки",
    "Beat 'em up",
    "Слэшеры"
  ],
  "platforms": [
    "PC"
  ],
  "base_price_rub": 30,
  "markup_rub": 500,
  "price_rub": 530,
  "original_price_rub": 629,
  "discount_percent": 77,
  "is_free": false,
  "trailer_video": null,
  "trailer_youtube_id": null,
  "screenshots": [
    "https://shared.akamai.steamstatic.com/store_item_assets/steam/apps/2792610/ss_5d048f6aba3e3aa82457c843af56911297b60d8b.1920x1080.jpg?t=1776682916",
    "https://shared.akamai.steamstatic.com/store_item_assets/steam/apps/2792610/ss_03034eca186f5278ef38507547653bd64a747d49.1920x1080.jpg?t=1776682916",
    "https://shared.akamai.steamstatic.com/store_item_assets/steam/apps/2792610/ss_c917532bff9550688abb2bfddbca1a6b930560ce.1920x1080.jpg?t=1776682916",
    "https://shared.akamai.steamstatic.com/store_item_assets/steam/apps/2792610/ss_202e72df66c4c822738f4d61beec10a4705697e0.1920x1080.jpg?t=1776682916",
    "https://shared.akamai.steamstatic.com/store_item_assets/steam/apps/2792610/ss_a274bb1721279eed10b8b552a08da926a2147f0d.1920x1080.jpg?t=1776682916",
    "https://shared.akamai.steamstatic.com/store_item_assets/steam/apps/2792610/ss_d0234e96b15d4edd8e1c315678b1e6d6fff87630.1920x1080.jpg?t=1776682916",
    "https://shared.akamai.steamstatic.com/store_item_assets/steam/apps/2792610/ss_57cca2538e648ef8c6bd0b5bf77c68716c603f00.1920x1080.jpg?t=1776682916",
    "https://shared.akamai.steamstatic.com/store_item_assets/steam/apps/2792610/ss_9f907a9b655d774015c65547f54945e12010f338.1920x1080.jpg?t=1776682916"
  ],
  "upsells": [],
  "source": "steam",
  "updated_at": "2026-07-07T09:59:34Z"
}