{
  "id": 3270,
  "title": "Painkiller Overdose",
  "cover": "https://cdn.cloudflare.steamstatic.com/steam/apps/3270/capsule_616x353.jpg",
  "hero": "https://cdn.cloudflare.steamstatic.com/steam/apps/3270/library_hero.jpg",
  "description": "Одобренный критиками и отмеченный наградами франчайзинг FPS вернулся! Набитый тоннами быстро идущего, заправленного адреналином однопользовательского и многопользовательского действа, Painkiller Overdose приносит с ним 6 инновационных новых демонических видов оружия, ошеломительную физику, карты с игрой молнии, более 40 чокнутых и извращенных монстров из Ада и гигантские конечные боссы, которые снесут вам крышу!\n • Приквел к конечному сиквелу, который соединяет сюжетную линию и связывает блуждающие концы.\n \n• Overdose привносит нового персонажа и сюжетную линию, которая рассматривает последствия победы Даниэля над Люцифером в оригинальном Painkiller!\n \n• 16 НОВЫХ уровней быстро идущего болеутоляющего действа!\n \n• Шесть НОВЫХ демонических видов оружия дают силу полубога душам, всюду ожидающих проклятия!\n \n• Изготовлено и разработано полностью Mindware Studios, давнишними адвокатами и фанатами игры.\n \n• Перетасованная колода Таро придает Велиалу новые силы и разрушительные комбинации.\n \n• Более 40 чокнутых и извращенных монстров из Ада.\n \n• Новые Конечные Боссы колоссального роста, охраняющие осыпающиеся владения Ада и входы в другие королевства!\n \n• Оживленные взгляды на многопользовательский режим привносят серию функций по отслеживанию статов и опций игрового сервера, предназначенные, чтобы пересмотреть многопользовательский опыт.\n \n• Многопользовательская совместимость с многопользовательскими картами и игровыми моделями оригинального Painkiller!",
  "description_short": "Одобренный критиками и отмеченный наградами франчайзинг FPS вернулся! Набитый тоннами быстро идущего, заправленного адреналином однопользовательского и многопользовательского действа, Painkiller Overdose приносит с ним 6 инновационных новых демонических видов оружия, ошеломительную физику, карты с игрой молнии, более 40 чокнутых и...",
  "genres": [
    "Экшен",
    "Шутеры от первого лица (FPS)",
    "Психологические хорроры"
  ],
  "platforms": [
    "PC"
  ],
  "base_price_rub": 229,
  "markup_rub": 500,
  "price_rub": 729,
  "original_price_rub": null,
  "discount_percent": 0,
  "is_free": false,
  "trailer_video": null,
  "trailer_youtube_id": null,
  "screenshots": [
    "https://shared.akamai.steamstatic.com/store_item_assets/steam/apps/3270/0000002937.1920x1080.jpg?t=1640259811",
    "https://shared.akamai.steamstatic.com/store_item_assets/steam/apps/3270/0000002938.1920x1080.jpg?t=1640259811",
    "https://shared.akamai.steamstatic.com/store_item_assets/steam/apps/3270/0000002939.1920x1080.jpg?t=1640259811",
    "https://shared.akamai.steamstatic.com/store_item_assets/steam/apps/3270/0000002940.1920x1080.jpg?t=1640259811",
    "https://shared.akamai.steamstatic.com/store_item_assets/steam/apps/3270/0000002941.1920x1080.jpg?t=1640259811",
    "https://shared.akamai.steamstatic.com/store_item_assets/steam/apps/3270/0000002942.1920x1080.jpg?t=1640259811",
    "https://shared.akamai.steamstatic.com/store_item_assets/steam/apps/3270/0000002943.1920x1080.jpg?t=1640259811",
    "https://shared.akamai.steamstatic.com/store_item_assets/steam/apps/3270/0000002944.1920x1080.jpg?t=1640259811"
  ],
  "upsells": [],
  "source": "steam",
  "updated_at": "2026-07-11T14:30:39Z"
}