{
  "id": 502820,
  "title": "Batman™: Arkham VR",
  "cover": "https://cdn.cloudflare.steamstatic.com/steam/apps/502820/capsule_616x353.jpg",
  "hero": "https://cdn.cloudflare.steamstatic.com/steam/apps/502820/library_hero.jpg",
  "description": "Batman™: Arkham VR погрузит вас в мир Темного Рыцаря и позволит по-настоящему ощутить себя Бэтменом – так, как никогда не бывало прежде.\n\r\n\n\r\nВзгляните на Готэм глазами величайшего детектива на планете и раскройте новое дело Аркхема.\n\r\n\n\r\nДумайте как Бэтмен. Используйте легендарные устройства в виртуальной реальности и предотвратите заговор, угрожающий жизни ближайших союзников Бэтмена.",
  "description_short": "Взгляните на Готэм глазами величайшего детектива на планете и раскройте новое дело Аркхема.",
  "genres": [
    "Приключения",
    "Психологические хорроры"
  ],
  "platforms": [
    "PC"
  ],
  "base_price_rub": 70,
  "markup_rub": 500,
  "price_rub": 570,
  "original_price_rub": 979,
  "discount_percent": 85,
  "is_free": false,
  "trailer_video": null,
  "trailer_youtube_id": null,
  "screenshots": [
    "https://shared.akamai.steamstatic.com/store_item_assets/steam/apps/502820/ss_bfb0ab888210c6e9c946371ff860fbe098138334.1920x1080.jpg?t=1773778770",
    "https://shared.akamai.steamstatic.com/store_item_assets/steam/apps/502820/ss_41cb1e2beff3c71b54fc632a2a18e2f9621c29cc.1920x1080.jpg?t=1773778770",
    "https://shared.akamai.steamstatic.com/store_item_assets/steam/apps/502820/ss_d0e93ca434fc24841543b5030100be8d43bd9d39.1920x1080.jpg?t=1773778770",
    "https://shared.akamai.steamstatic.com/store_item_assets/steam/apps/502820/ss_9e9add450d9e159e89ced0267b9b74b92b490399.1920x1080.jpg?t=1773778770",
    "https://shared.akamai.steamstatic.com/store_item_assets/steam/apps/502820/ss_9e4e31da7eaadfe260f5bd355cb590680e3f16ac.1920x1080.jpg?t=1773778770",
    "https://shared.akamai.steamstatic.com/store_item_assets/steam/apps/502820/ss_3be5bc8c0c49dbf60eef80a550880427a4a13171.1920x1080.jpg?t=1773778770"
  ],
  "upsells": [],
  "source": "steam",
  "updated_at": "2026-07-08T09:10:45Z"
}