{
  "id": 6300,
  "title": "Dreamfall: The Longest Journey",
  "cover": "https://shared.akamai.steamstatic.com/store_item_assets/steam/apps/6300/header.jpg?t=1592476034",
  "hero": "https://cdn.cloudflare.steamstatic.com/steam/apps/6300/library_hero.jpg",
  "description": "Dreamfall: The Longest Journey, обладатель нескольких призов E3 как лучшая игра в своем жанре — продолжение саги, начатой отмеченной наградами The Longest Journey, считающейся самой лучшей когда-либо сделанной приключенческой игрой. В Dreamfall игроки будут вовлечены в эпическое исследовательское путешествие по мере того, как они рискнут следовать захватывающей и волнующей сюжетной линии. Особенности Dreamfall — это полностью интерактивный мир, где прекрасная музыка, сногсшибательная графика, обаятельные герои и нелинейный геймплей обещают ввести жанр приключений в новую эру. Приготовьтесь к возвышенному, фантастическому и яркому переживанию от игры.\n • Бесподобное разнообразие геймплея Никогда раньше приключенческая игра не предлагала столько вариаций геймплея! Используйте ваши мозги или мышцы; крадите, сражайтесь или общайтесь; в Dreamfall вы делаете выбор, который отражается в игре, где вы никогда не можете быть уверены, что произойдет дальше.\n \n• Три игровых персонажа Окунитесь в историю с трех различных точек зрения и узнайте, как их судьбы переплетутся в эпическом финале. Каждый персонаж обладает уникальными способностями и взглядами на мир, предлагая вам определенные вариации геймплея.\n \n• Три мира Dreamfall включает в себя три прекрасно реализованных мира, различных персонажей и ошеломляющее количество детализированных локаций. Путешествуйте по футуристической версии нашей Земли, погрузитесь в волшебное королевство и разгадайте тайны Зимы.\n \n• Уникальное взаимодействие с миром Преодолевая разрыв между классическим приключением «указал и щелкнул», где вы могли щелкнуть на любой заданной точке на экране, и боевым приключением, где вам нужно подходить к объекту для взаимодействия с ним, Dreamfall представляет совершенно новую особенность фокусного поля. В этом легком для пользования контекстно-зависимом интерфейсе вы можете рассматривать все видимое окружение глазами героев и использовать его для получения сведений об отдаленных объектах, а также запуска возможностей удаленного геймплея.\n \n• Продуманная «остросюжетная» линия Dreamfall преподносит продуманную и неотразимую сюжетную линию, сочетающую в себе футуризм, фантастику и спиритизм с историей убийства, обмана и сговора, угрожающего самому нашему существованию. Принося классическую приключенческую игру в мир современной экшен-игры, Dreamfall преподносит редкий и особенный опыт повествований.\n \n• Великолепный звук и музыка Слушайте трогающую и грандиозную звуковую дорожку в окружении 7.1. Услышьте потрясающие голоса, записанные более чем 50 профессиональными актерами, и наслаждайтесь звуковым сопровождением, заставляющим игроков затаить дыхание.\n \n• Игра для всех 50% игравших в оригинальную The Longest Journey были женщинами. С его кинематическим подходом, правдоподобными героями, продуманной сюжетной линией и легким для восприятия интерфейсом, Dreamfall — это игра, которую любой подросток или взрослый может принять и полюбить, независимо от их игрового прошлого.",
  "description_short": "Dreamfall: The Longest Journey, обладатель нескольких призов E3 как лучшая игра в своем жанре — продолжение саги, начатой отмеченной наградами The Longest Journey, считающейся самой лучшей когда-либо сделанной приключенческой игрой.",
  "genres": [
    "Приключения",
    "Головоломки",
    "Экшен"
  ],
  "platforms": [
    "PC"
  ],
  "base_price_rub": 216,
  "markup_rub": 500,
  "price_rub": 716,
  "original_price_rub": 1222,
  "discount_percent": 70,
  "is_free": false,
  "trailer_video": null,
  "trailer_youtube_id": null,
  "screenshots": [
    "https://shared.akamai.steamstatic.com/store_item_assets/steam/apps/6300/0000001130.1920x1080.jpg?t=1592476034",
    "https://shared.akamai.steamstatic.com/store_item_assets/steam/apps/6300/0000001131.1920x1080.jpg?t=1592476034",
    "https://shared.akamai.steamstatic.com/store_item_assets/steam/apps/6300/0000001132.1920x1080.jpg?t=1592476034",
    "https://shared.akamai.steamstatic.com/store_item_assets/steam/apps/6300/0000001133.1920x1080.jpg?t=1592476034",
    "https://shared.akamai.steamstatic.com/store_item_assets/steam/apps/6300/0000001134.1920x1080.jpg?t=1592476034",
    "https://shared.akamai.steamstatic.com/store_item_assets/steam/apps/6300/0000001135.1920x1080.jpg?t=1592476034",
    "https://shared.akamai.steamstatic.com/store_item_assets/steam/apps/6300/0000001136.1920x1080.jpg?t=1592476034",
    "https://shared.akamai.steamstatic.com/store_item_assets/steam/apps/6300/0000001137.1920x1080.jpg?t=1592476034"
  ],
  "upsells": [],
  "source": "steam",
  "updated_at": "2026-07-07T20:20:12Z"
}