{
  "id": 8140,
  "title": "Tomb Raider: Underworld",
  "cover": "https://cdn.cloudflare.steamstatic.com/steam/apps/8140/capsule_616x353.jpg",
  "hero": "https://cdn.cloudflare.steamstatic.com/steam/apps/8140/library_hero.jpg",
  "description": "Tomb Raider: Underworld является новой вехой в развитии исследовательских игр. Бесстрашная авантюристка Лара Крофт отправится в самые отдалённые точки земного шара, воссозданные до мельчайших подробностей. Умопомрачительная проработка локаций даёт по истине фотореалистический зрительный ряд, вознося преодоление препятствий и моральный выбор на качественно новый уровень. \n• Изучите окрестности: доберитесь до новых высот с помощью большого числа акробатических трюков, применяйте предметы из окружения, чтобы открыть новый путь для дальнейшего исследования. \n\n• Исследуйте легендарные и неизведанные места: раскройте загадки древних подземелий, скрытых в таиландском прибрежье, ледяных арктических островах, мексиканских джунглях и других областях. \n\n• Коварные и непредсказуемые ловушки: каждый игровой уровень представляет собой сложную многоступенчатую головоломку, лежащую в основе интерактивной исследуемой области, что даёт б́ольшую гибкость в выборе пути её решения. \n\n• Новые боевые приёмы: выбирайте между обезвреживанием и убийством противников, поражайте сразу несколько целей с помощью новой системы двойного прицела, стреляйте с одной руки, второй зацепившись за уступ. \n\n• Новейшее современное оборудование: чтобы сориентироваться в пространстве, воспользуйтесь последними достижениями техники в обновленном инвентаре Лары, как-то:\n - Звукосонарная карта: революционно новое устройство, которое, посылая ультразвуковые импульсы, строит трёхмерную карту окрестностей, идеально подходит для обнаружения спрятанных предметов и потайных ходов.\n - Захват: магнитная кошка с тросом сверхвысокого натяжения, созданная для взбирания и спускания по отвесным поверхностям, выполнения пробежки по стене, а также передвигания окружающих предметов.\n - Гибридный мотоцикл-вездеход: уникальное транспортное средство, способное преодолевать любые преграды, будь то грязь, снег или лёд.",
  "description_short": "Tomb Raider: Underworld является новой вехой в развитии исследовательских игр. Бесстрашная авантюристка Лара Крофт отправится в самые отдалённые точки земного шара, воссозданные до мельчайших подробностей.",
  "genres": [
    "Приключения",
    "Экшен",
    "Головоломки",
    "Платформеры",
    "Экшен-адвенчуры",
    "Шутеры от первого лица (FPS)"
  ],
  "platforms": [
    "PC"
  ],
  "base_price_rub": 297,
  "markup_rub": 500,
  "price_rub": 797,
  "original_price_rub": null,
  "discount_percent": 0,
  "is_free": false,
  "trailer_video": null,
  "trailer_youtube_id": null,
  "screenshots": [
    "https://shared.akamai.steamstatic.com/store_item_assets/steam/apps/8140/0000005727.1920x1080.jpg?t=1729009496",
    "https://shared.akamai.steamstatic.com/store_item_assets/steam/apps/8140/0000005728.1920x1080.jpg?t=1729009496",
    "https://shared.akamai.steamstatic.com/store_item_assets/steam/apps/8140/0000005729.1920x1080.jpg?t=1729009496",
    "https://shared.akamai.steamstatic.com/store_item_assets/steam/apps/8140/0000005730.1920x1080.jpg?t=1729009496",
    "https://shared.akamai.steamstatic.com/store_item_assets/steam/apps/8140/0000005731.1920x1080.jpg?t=1729009496",
    "https://shared.akamai.steamstatic.com/store_item_assets/steam/apps/8140/0000005732.1920x1080.jpg?t=1729009496",
    "https://shared.akamai.steamstatic.com/store_item_assets/steam/apps/8140/0000005733.1920x1080.jpg?t=1729009496",
    "https://shared.akamai.steamstatic.com/store_item_assets/steam/apps/8140/0000005734.1920x1080.jpg?t=1729009496"
  ],
  "upsells": [],
  "source": "steam",
  "updated_at": "2026-07-17T03:52:23Z"
}