{
  "id": 979690,
  "title": "The Ascent",
  "cover": "https://cdn.cloudflare.steamstatic.com/steam/apps/979690/capsule_616x353.jpg",
  "hero": "https://cdn.cloudflare.steamstatic.com/steam/apps/979690/library_hero.jpg",
  "description": "The Ascent — экшн-RPG в духе киберпанка с режимами одиночной и кооперативной игры.\n\nДобро пожаловать на Велес! Вы — подневольный «Асцент Груп», крупнейшей корпорации на планете, которая владеет здесь всем и вся. Внезапно «АГ» прекращает свое существование, и вы попадаете в водоворот опасных событий. Системы безопасности выходят из строя, конкуренты стремятся захватить власть, а преступные группировки — укрепиться на черном рынке. Остановите захватчиков и докопайтесь до причин произошедшего! \n\nВы — собственность корпорации. Сумеете выжить без нее?ОДИНОЧНЫЙ И КООПЕРАТИВНЫЙ РЕЖИМЫ\n\nВы можете пройти всю игру в одиночку или же объединиться с друзьями в команду до четырех игроков, чтобы сыграть локально или по сети Интернет.ЯРОСТНЫЕ ПЕРЕСТРЕЛКИ\n\nМножество пушек и смертоносных гаджетов, изменение высоты прицела, использование укрытий и особенностей местности, а также смена тактики помогут эффектно расправиться с врагами.ЭЛЕМЕНТЫ RPG\n\nИзменяйте персонажа под свой стиль прохождения. Повышайте уровень, улучшайте навыки и устанавливайте разнообразные аугментации, чтобы не оставить противникам ни единого шанса.ЭФФЕКТНЫЙ МИР В СТИЛЕ КИБЕРПАНКА\n\nВам предстоит исследовать все районы аркологии «Асцент Груп», пройти по трущобам и элитным комплексам, обрести новых друзей и врагов, а также найти горы добычи.",
  "description_short": "The Ascent — экшн-RPG в духе киберпанка с режимами одиночной и кооперативной игры. Владеющая всем (и вами) мегакорпорация «Асцент Груп» внезапно прекращает свое существование. Сумеете выжить без нее?",
  "genres": [
    "Экшен",
    "Шутеры от первого лица (FPS)",
    "Песочницы (Sandbox)",
    "Приключения",
    "Экшен-РПГ (Action-RPG)"
  ],
  "platforms": [
    "PC"
  ],
  "base_price_rub": 1094,
  "markup_rub": 500,
  "price_rub": 1594,
  "original_price_rub": null,
  "discount_percent": 0,
  "is_free": false,
  "trailer_video": null,
  "trailer_youtube_id": null,
  "screenshots": [
    "https://shared.akamai.steamstatic.com/store_item_assets/steam/apps/979690/ss_8632397359039045fc6c638f843272bf775b7efa.1920x1080.jpg?t=1772590323",
    "https://shared.akamai.steamstatic.com/store_item_assets/steam/apps/979690/ss_3708227bd120f1cd9987ba1c49ddabaec15ed0e3.1920x1080.jpg?t=1772590323",
    "https://shared.akamai.steamstatic.com/store_item_assets/steam/apps/979690/ss_4c29d46c7240c99b5e755164196153a9797ceeb6.1920x1080.jpg?t=1772590323",
    "https://shared.akamai.steamstatic.com/store_item_assets/steam/apps/979690/ss_3dc5f44c56f68f053d47a55e51751bf30c085b3c.1920x1080.jpg?t=1772590323",
    "https://shared.akamai.steamstatic.com/store_item_assets/steam/apps/979690/ss_0e5bdb1ed1a6c581ba46f1489b4a6bfe194aba4d.1920x1080.jpg?t=1772590323",
    "https://shared.akamai.steamstatic.com/store_item_assets/steam/apps/979690/ss_ea7287c85d79b40b2ea29bf9907d6fbe9c057787.1920x1080.jpg?t=1772590323",
    "https://shared.akamai.steamstatic.com/store_item_assets/steam/apps/979690/ss_2d21828d80f3ce1de7a0fa31f93c7805d913f55b.1920x1080.jpg?t=1772590323",
    "https://shared.akamai.steamstatic.com/store_item_assets/steam/apps/979690/ss_c7d70ac76c1d606d79a488cadcb9f73a206a27db.1920x1080.jpg?t=1772590323"
  ],
  "upsells": [
    {
      "id": 1802470,
      "name": "The Ascent - Cyber Heist",
      "base_price_rub": 360,
      "markup_rub": 500,
      "price_rub": 860,
      "cover": "https://shared.akamai.steamstatic.com/store_item_assets/steam/apps/1802470/header.jpg?t=1772501599"
    },
    {
      "id": 1802451,
      "name": "The Ascent - Cyber Warrior Pack",
      "base_price_rub": 188,
      "markup_rub": 500,
      "price_rub": 688,
      "cover": "https://shared.akamai.steamstatic.com/store_item_assets/steam/apps/1802451/header.jpg?t=1772501602"
    },
    {
      "id": 1802450,
      "name": "The Ascent - CyberSec Pack",
      "base_price_rub": 188,
      "markup_rub": 500,
      "price_rub": 688,
      "cover": "https://shared.akamai.steamstatic.com/store_item_assets/steam/apps/1802450/header.jpg?t=1772501600"
    },
    {
      "id": 1702920,
      "name": "The Ascent Soundtrack",
      "base_price_rub": 171,
      "markup_rub": 500,
      "price_rub": 671,
      "cover": "https://shared.akamai.steamstatic.com/store_item_assets/steam/apps/1702920/header.jpg?t=1772501610"
    },
    {
      "id": 2081570,
      "name": "The Ascent - Cyber Heist - Soundtrack",
      "base_price_rub": 119,
      "markup_rub": 500,
      "price_rub": 619,
      "cover": "https://shared.akamai.steamstatic.com/store_item_assets/steam/apps/2081570/header.jpg?t=1772501611"
    },
    {
      "id": 3896950,
      "name": "The Ascent - Artbook + Weapon Pack",
      "base_price_rub": 119,
      "markup_rub": 500,
      "price_rub": 619,
      "cover": "https://shared.akamai.steamstatic.com/store_item_assets/steam/apps/3896950/c2a283929997e99cc2fd1875c791d6c1f8709dd3/header.jpg?t=1772501605"
    }
  ],
  "source": "steam",
  "updated_at": "2026-07-15T20:01:17Z"
}